pydrought/__init__.py
pydrought/gui0.0.py
pydrought/spi.py
pydrought/util.py
pydrought/data/Rain.csv
pydrought/data/commadelimited_monthly_wdates.csv
pydrought/data/commadelimited_monthly_wdates_SPI_M_01_03_06.csv
pydrought-0.2.dist-info/METADATA
pydrought-0.2.dist-info/WHEEL
pydrought-0.2.dist-info/top_level.txt
pydrought-0.2.dist-info/RECORD
