Metadata-Version: 2.1
Name: pydrought
Version: 0.2
Summary: Standardized Precipitation Index
Home-page: http://gau.ac.ir/
Author: Ch B Komaki
Author-email: gmail@gmail.com
License: UNKNOWN
Platform: UNKNOWN
